setup.py
mapmatching_benchmark/__init__.py
mapmatching_benchmark/circle_test.py
mapmatching_benchmark/common.py
mapmatching_benchmark/conversion.py
mapmatching_benchmark/correct_cost_computation_count.py
mapmatching_benchmark/generate_config.py
mapmatching_benchmark/graph_based_map_matcher.py
mapmatching_benchmark/init.py
mapmatching_benchmark/plot_accuracy_vs_period_graph.py
mapmatching_benchmark/plot_comparison_graph.py
mapmatching_benchmark/plot_cost_count_vs_period_graph.py
mapmatching_benchmark/plot_time_vs_period_graph.py
mapmatching_benchmark/results.py
mapmatching_benchmark/subsampling.py
mapmatching_benchmark/tester.py
mapmatching_benchmark.egg-info/PKG-INFO
mapmatching_benchmark.egg-info/SOURCES.txt
mapmatching_benchmark.egg-info/dependency_links.txt
mapmatching_benchmark.egg-info/requires.txt
mapmatching_benchmark.egg-info/top_level.txt
mapmatching_benchmark/config/__init__.py
mapmatching_benchmark/config/images.py
mapmatching_benchmark/config/machine_learning_benchmark_config.py
mapmatching_benchmark/resources/__init__.py
mapmatching_benchmark/resources/config.cfg