Metadata-Version: 1.0
Name: mapmatching-benchmark
Version: 0.1
Summary: Map Matching Benchmark
Home-page: UNKNOWN
Author: F.I.D.O.
Author-email: david.fido.fiedler@gmail.com
License: MIT
Platform: UNKNOWN
